[
  {
    "publisher": "Wiley",
    "issue": "1",
    "DOI": "10.1002/cac2.12005",
    "type": "article-journal",
    "page": "43-59",
    "source": "Crossref",
    "title": "Spectrum of EGFR aberrations and potential clinical implications: insights from integrative pan‐cancer analysis",
    "volume": "40",
    "author": [
      {
        "given": "Haijing",
        "family": "Liu"
      },
      {
        "given": "Bo",
        "family": "Zhang"
      },
      {
        "given": "Zhifu",
        "family": "Sun"
      }
    ],
    "container-title": "Cancer Communications",
    "language": "en",
    "issued": {
      "date-parts": [
        [
          2020,
          1
        ]
      ]
    },
    "URL": "https://doi.org/ghsz4b",
    "container-title-short": "Cancer Communications",
    "PMCID": "PMC7163653",
    "PMID": "32067422",
    "id": "rzy1RWeA",
    "note": "This CSL Item was generated by Manubot v0.5.5 from its persistent identifier (standard_id).\nstandard_id: doi:10.1002/cac2.12005"
  },
  {
    "publisher": "Elsevier BV",
    "issue": "3",
    "DOI": "10.1016/j.cels.2018.03.002",
    "type": "article-journal",
    "page": "271-281.e7",
    "source": "Crossref",
    "title": "Scalable Open Science Approach for Mutation Calling of Tumor Exomes Using Multiple Genomic Pipelines",
    "volume": "6",
    "author": [
      {
        "given": "Kyle",
        "family": "Ellrott"
      },
      {
        "given": "Matthew H.",
        "family": "Bailey"
      },
      {
        "given": "Gordon",
        "family": "Saksena"
      },
      {
        "given": "Kyle R.",
        "family": "Covington"
      },
      {
        "given": "Cyriac",
        "family": "Kandoth"
      },
      {
        "given": "Chip",
        "family": "Stewart"
      },
      {
        "given": "Julian",
        "family": "Hess"
      },
      {
        "given": "Singer",
        "family": "Ma"
      },
      {
        "given": "Kami E.",
        "family": "Chiotti"
      },
      {
        "given": "Michael",
        "family": "McLellan"
      },
      {
        "given": "Heidi J.",
        "family": "Sofia"
      },
      {
        "given": "Carolyn",
        "family": "Hutter"
      },
      {
        "given": "Gad",
        "family": "Getz"
      },
      {
        "given": "David",
        "family": "Wheeler"
      },
      {
        "given": "Li",
        "family": "Ding"
      },
      {
        "given": "Samantha J.",
        "family": "Caesar-Johnson"
      },
      {
        "given": "John A.",
        "family": "Demchok"
      },
      {
        "given": "Ina",
        "family": "Felau"
      },
      {
        "given": "Melpomeni",
        "family": "Kasapi"
      },
      {
        "given": "Martin L.",
        "family": "Ferguson"
      },
      {
        "given": "Carolyn M.",
        "family": "Hutter"
      },
      {
        "given": "Heidi J.",
        "family": "Sofia"
      },
      {
        "given": "Roy",
        "family": "Tarnuzzer"
      },
      {
        "given": "Zhining",
        "family": "Wang"
      },
      {
        "given": "Liming",
        "family": "Yang"
      },
      {
        "given": "Jean C.",
        "family": "Zenklusen"
      },
      {
        "given": "Jiashan (Julia)",
        "family": "Zhang"
      },
      {
        "given": "Sudha",
        "family": "Chudamani"
      },
      {
        "given": "Jia",
        "family": "Liu"
      },
      {
        "given": "Laxmi",
        "family": "Lolla"
      },
      {
        "given": "Rashi",
        "family": "Naresh"
      },
      {
        "given": "Todd",
        "family": "Pihl"
      },
      {
        "given": "Qiang",
        "family": "Sun"
      },
      {
        "given": "Yunhu",
        "family": "Wan"
      },
      {
        "given": "Ye",
        "family": "Wu"
      },
      {
        "given": "Juok",
        "family": "Cho"
      },
      {
        "given": "Timothy",
        "family": "DeFreitas"
      },
      {
        "given": "Scott",
        "family": "Frazer"
      },
      {
        "given": "Nils",
        "family": "Gehlenborg"
      },
      {
        "given": "Gad",
        "family": "Getz"
      },
      {
        "given": "David I.",
        "family": "Heiman"
      },
      {
        "given": "Jaegil",
        "family": "Kim"
      },
      {
        "given": "Michael S.",
        "family": "Lawrence"
      },
      {
        "given": "Pei",
        "family": "Lin"
      },
      {
        "given": "Sam",
        "family": "Meier"
      },
      {
        "given": "Michael S.",
        "family": "Noble"
      },
      {
        "given": "Gordon",
        "family": "Saksena"
      },
      {
        "given": "Doug",
        "family": "Voet"
      },
      {
        "given": "Hailei",
        "family": "Zhang"
      },
      {
        "given": "Brady",
        "family": "Bernard"
      },
      {
        "given": "Nyasha",
        "family": "Chambwe"
      },
      {
        "given": "Varsha",
        "family": "Dhankani"
      },
      {
        "given": "Theo",
        "family": "Knijnenburg"
      },
      {
        "given": "Roger",
        "family": "Kramer"
      },
      {
        "given": "Kalle",
        "family": "Leinonen"
      },
      {
        "given": "Yuexin",
        "family": "Liu"
      },
      {
        "given": "Michael",
        "family": "Miller"
      },
      {
        "given": "Sheila",
        "family": "Reynolds"
      },
      {
        "given": "Ilya",
        "family": "Shmulevich"
      },
      {
        "given": "Vesteinn",
        "family": "Thorsson"
      },
      {
        "given": "Wei",
        "family": "Zhang"
      },
      {
        "given": "Rehan",
        "family": "Akbani"
      },
      {
        "given": "Bradley M.",
        "family": "Broom"
      },
      {
        "given": "Apurva M.",
        "family": "Hegde"
      },
      {
        "given": "Zhenlin",
        "family": "Ju"
      },
      {
        "given": "Rupa S.",
        "family": "Kanchi"
      },
      {
        "given": "Anil",
        "family": "Korkut"
      },
      {
        "given": "Jun",
        "family": "Li"
      },
      {
        "given": "Han",
        "family": "Liang"
      },
      {
        "given": "Shiyun",
        "family": "Ling"
      },
      {
        "given": "Wenbin",
        "family": "Liu"
      },
      {
        "given": "Yiling",
        "family": "Lu"
      },
      {
        "given": "Gordon B.",
        "family": "Mills"
      },
      {
        "given": "Kwok-Shing",
        "family": "Ng"
      },
      {
        "given": "Arvind",
        "family": "Rao"
      },
      {
        "given": "Michael",
        "family": "Ryan"
      },
      {
        "given": "Jing",
        "family": "Wang"
      },
      {
        "given": "John N.",
        "family": "Weinstein"
      },
      {
        "given": "Jiexin",
        "family": "Zhang"
      },
      {
        "given": "Adam",
        "family": "Abeshouse"
      },
      {
        "given": "Joshua",
        "family": "Armenia"
      },
      {
        "given": "Debyani",
        "family": "Chakravarty"
      },
      {
        "given": "Walid K.",
        "family": "Chatila"
      },
      {
        "given": "Ino",
        "family": "de Bruijn"
      },
      {
        "given": "Jianjiong",
        "family": "Gao"
      },
      {
        "given": "Benjamin E.",
        "family": "Gross"
      },
      {
        "given": "Zachary J.",
        "family": "Heins"
      },
      {
        "given": "Ritika",
        "family": "Kundra"
      },
      {
        "given": "Konnor",
        "family": "La"
      },
      {
        "given": "Marc",
        "family": "Ladanyi"
      },
      {
        "given": "Augustin",
        "family": "Luna"
      },
      {
        "given": "Moriah G.",
        "family": "Nissan"
      },
      {
        "given": "Angelica",
        "family": "Ochoa"
      },
      {
        "given": "Sarah M.",
        "family": "Phillips"
      },
      {
        "given": "Ed",
        "family": "Reznik"
      },
      {
        "given": "Francisco",
        "family": "Sanchez-Vega"
      },
      {
        "given": "Chris",
        "family": "Sander"
      },
      {
        "given": "Nikolaus",
        "family": "Schultz"
      },
      {
        "given": "Robert",
        "family": "Sheridan"
      },
      {
        "given": "S. Onur",
        "family": "Sumer"
      },
      {
        "given": "Yichao",
        "family": "Sun"
      },
      {
        "given": "Barry S.",
        "family": "Taylor"
      },
      {
        "given": "Jioajiao",
        "family": "Wang"
      },
      {
        "given": "Hongxin",
        "family": "Zhang"
      },
      {
        "given": "Pavana",
        "family": "Anur"
      },
      {
        "given": "Myron",
        "family": "Peto"
      },
      {
        "given": "Paul",
        "family": "Spellman"
      },
      {
        "given": "Christopher",
        "family": "Benz"
      },
      {
        "given": "Joshua M.",
        "family": "Stuart"
      },
      {
        "given": "Christopher K.",
        "family": "Wong"
      },
      {
        "given": "Christina",
        "family": "Yau"
      },
      {
        "given": "D. Neil",
        "family": "Hayes"
      },
      {
        "family": "Parker"
      },
      {
        "given": "Matthew D.",
        "family": "Wilkerson"
      },
      {
        "given": "Adrian",
        "family": "Ally"
      },
      {
        "given": "Miruna",
        "family": "Balasundaram"
      },
      {
        "given": "Reanne",
        "family": "Bowlby"
      },
      {
        "given": "Denise",
        "family": "Brooks"
      },
      {
        "given": "Rebecca",
        "family": "Carlsen"
      },
      {
        "given": "Eric",
        "family": "Chuah"
      },
      {
        "given": "Noreen",
        "family": "Dhalla"
      },
      {
        "given": "Robert",
        "family": "Holt"
      },
      {
        "given": "Steven J.M.",
        "family": "Jones"
      },
      {
        "given": "Katayoon",
        "family": "Kasaian"
      },
      {
        "given": "Darlene",
        "family": "Lee"
      },
      {
        "given": "Yussanne",
        "family": "Ma"
      },
      {
        "given": "Marco A.",
        "family": "Marra"
      },
      {
        "given": "Michael",
        "family": "Mayo"
      },
      {
        "given": "Richard A.",
        "family": "Moore"
      },
      {
        "given": "Andrew J.",
        "family": "Mungall"
      },
      {
        "given": "Karen",
        "family": "Mungall"
      },
      {
        "given": "A. Gordon",
        "family": "Robertson"
      },
      {
        "given": "Sara",
        "family": "Sadeghi"
      },
      {
        "given": "Jacqueline E.",
        "family": "Schein"
      },
      {
        "given": "Payal",
        "family": "Sipahimalani"
      },
      {
        "given": "Angela",
        "family": "Tam"
      },
      {
        "given": "Nina",
        "family": "Thiessen"
      },
      {
        "given": "Kane",
        "family": "Tse"
      },
      {
        "given": "Tina",
        "family": "Wong"
      },
      {
        "given": "Ashton C.",
        "family": "Berger"
      },
      {
        "given": "Rameen",
        "family": "Beroukhim"
      },
      {
        "given": "Andrew D.",
        "family": "Cherniack"
      },
      {
        "given": "Carrie",
        "family": "Cibulskis"
      },
      {
        "given": "Stacey B.",
        "family": "Gabriel"
      },
      {
        "given": "Galen F.",
        "family": "Gao"
      },
      {
        "given": "Gavin",
        "family": "Ha"
      },
      {
        "given": "Matthew",
        "family": "Meyerson"
      },
      {
        "given": "Steven E.",
        "family": "Schumacher"
      },
      {
        "given": "Juliann",
        "family": "Shih"
      },
      {
        "given": "Melanie H.",
        "family": "Kucherlapati"
      },
      {
        "given": "Raju S.",
        "family": "Kucherlapati"
      },
      {
        "given": "Stephen",
        "family": "Baylin"
      },
      {
        "given": "Leslie",
        "family": "Cope"
      },
      {
        "given": "Ludmila",
        "family": "Danilova"
      },
      {
        "given": "Moiz S.",
        "family": "Bootwalla"
      },
      {
        "given": "Phillip H.",
        "family": "Lai"
      },
      {
        "given": "Dennis T.",
        "family": "Maglinte"
      },
      {
        "given": "David J.",
        "family": "Van Den Berg"
      },
      {
        "given": "Daniel J.",
        "family": "Weisenberger"
      },
      {
        "given": "J. Todd",
        "family": "Auman"
      },
      {
        "given": "Saianand",
        "family": "Balu"
      },
      {
        "given": "Tom",
        "family": "Bodenheimer"
      },
      {
        "given": "Cheng",
        "family": "Fan"
      },
      {
        "given": "Katherine A.",
        "family": "Hoadley"
      },
      {
        "given": "Alan P.",
        "family": "Hoyle"
      },
      {
        "given": "Stuart R.",
        "family": "Jefferys"
      },
      {
        "given": "Corbin D.",
        "family": "Jones"
      },
      {
        "given": "Shaowu",
        "family": "Meng"
      },
      {
        "given": "Piotr A.",
        "family": "Mieczkowski"
      },
      {
        "given": "Lisle E.",
        "family": "Mose"
      },
      {
        "given": "Amy H.",
        "family": "Perou"
      },
      {
        "given": "Charles M.",
        "family": "Perou"
      },
      {
        "given": "Jeffrey",
        "family": "Roach"
      },
      {
        "given": "Yan",
        "family": "Shi"
      },
      {
        "given": "Janae V.",
        "family": "Simons"
      },
      {
        "given": "Tara",
        "family": "Skelly"
      },
      {
        "given": "Matthew G.",
        "family": "Soloway"
      },
      {
        "given": "Donghui",
        "family": "Tan"
      },
      {
        "given": "Umadevi",
        "family": "Veluvolu"
      },
      {
        "given": "Huihui",
        "family": "Fan"
      },
      {
        "given": "Toshinori",
        "family": "Hinoue"
      },
      {
        "given": "Peter W.",
        "family": "Laird"
      },
      {
        "given": "Hui",
        "family": "Shen"
      },
      {
        "given": "Wanding",
        "family": "Zhou"
      },
      {
        "given": "Michelle",
        "family": "Bellair"
      },
      {
        "given": "Kyle",
        "family": "Chang"
      },
      {
        "given": "Kyle",
        "family": "Covington"
      },
      {
        "given": "Chad J.",
        "family": "Creighton"
      },
      {
        "given": "Huyen",
        "family": "Dinh"
      },
      {
        "given": "HarshaVardhan",
        "family": "Doddapaneni"
      },
      {
        "given": "Lawrence A.",
        "family": "Donehower"
      },
      {
        "given": "Jennifer",
        "family": "Drummond"
      },
      {
        "given": "Richard A.",
        "family": "Gibbs"
      },
      {
        "given": "Robert",
        "family": "Glenn"
      },
      {
        "given": "Walker",
        "family": "Hale"
      },
      {
        "given": "Yi",
        "family": "Han"
      },
      {
        "given": "Jianhong",
        "family": "Hu"
      },
      {
        "given": "Viktoriya",
        "family": "Korchina"
      },
      {
        "given": "Sandra",
        "family": "Lee"
      },
      {
        "given": "Lora",
        "family": "Lewis"
      },
      {
        "given": "Wei",
        "family": "Li"
      },
      {
        "given": "Xiuping",
        "family": "Liu"
      },
      {
        "given": "Margaret",
        "family": "Morgan"
      },
      {
        "given": "Donna",
        "family": "Morton"
      },
      {
        "given": "Donna",
        "family": "Muzny"
      },
      {
        "given": "Jireh",
        "family": "Santibanez"
      },
      {
        "given": "Margi",
        "family": "Sheth"
      },
      {
        "given": "Eve",
        "family": "Shinbrot"
      },
      {
        "given": "Linghua",
        "family": "Wang"
      },
      {
        "given": "Min",
        "family": "Wang"
      },
      {
        "given": "David A.",
        "family": "Wheeler"
      },
      {
        "given": "Liu",
        "family": "Xi"
      },
      {
        "given": "Fengmei",
        "family": "Zhao"
      },
      {
        "given": "Julian",
        "family": "Hess"
      },
      {
        "given": "Elizabeth L.",
        "family": "Appelbaum"
      },
      {
        "given": "Matthew",
        "family": "Bailey"
      },
      {
        "given": "Matthew G.",
        "family": "Cordes"
      },
      {
        "given": "Li",
        "family": "Ding"
      },
      {
        "given": "Catrina C.",
        "family": "Fronick"
      },
      {
        "given": "Lucinda A.",
        "family": "Fulton"
      },
      {
        "given": "Robert S.",
        "family": "Fulton"
      },
      {
        "given": "Cyriac",
        "family": "Kandoth"
      },
      {
        "given": "Elaine R.",
        "family": "Mardis"
      },
      {
        "given": "Michael D.",
        "family": "McLellan"
      },
      {
        "given": "Christopher A.",
        "family": "Miller"
      },
      {
        "given": "Heather K.",
        "family": "Schmidt"
      },
      {
        "given": "Richard K.",
        "family": "Wilson"
      },
      {
        "given": "Daniel",
        "family": "Crain"
      },
      {
        "given": "Erin",
        "family": "Curley"
      },
      {
        "given": "Johanna",
        "family": "Gardner"
      },
      {
        "given": "Kevin",
        "family": "Lau"
      },
      {
        "given": "David",
        "family": "Mallery"
      },
      {
        "given": "Scott",
        "family": "Morris"
      },
      {
        "given": "Joseph",
        "family": "Paulauskis"
      },
      {
        "given": "Robert",
        "family": "Penny"
      },
      {
        "given": "Candace",
        "family": "Shelton"
      },
      {
        "given": "Troy",
        "family": "Shelton"
      },
      {
        "given": "Mark",
        "family": "Sherman"
      },
      {
        "given": "Eric",
        "family": "Thompson"
      },
      {
        "given": "Peggy",
        "family": "Yena"
      },
      {
        "given": "Jay",
        "family": "Bowen"
      },
      {
        "given": "Julie M.",
        "family": "Gastier-Foster"
      },
      {
        "given": "Mark",
        "family": "Gerken"
      },
      {
        "given": "Kristen M.",
        "family": "Leraas"
      },
      {
        "given": "Tara M.",
        "family": "Lichtenberg"
      },
      {
        "given": "Nilsa C.",
        "family": "Ramirez"
      },
      {
        "given": "Lisa",
        "family": "Wise"
      },
      {
        "given": "Erik",
        "family": "Zmuda"
      },
      {
        "given": "Niall",
        "family": "Corcoran"
      },
      {
        "given": "Tony",
        "family": "Costello"
      },
      {
        "given": "Christopher",
        "family": "Hovens"
      },
      {
        "given": "Andre L.",
        "family": "Carvalho"
      },
      {
        "given": "Ana C.",
        "family": "de Carvalho"
      },
      {
        "given": "José H.",
        "family": "Fregnani"
      },
      {
        "given": "Adhemar",
        "family": "Longatto-Filho"
      },
      {
        "given": "Rui M.",
        "family": "Reis"
      },
      {
        "given": "Cristovam",
        "family": "Scapulatempo-Neto"
      },
      {
        "given": "Henrique C.S.",
        "family": "Silveira"
      },
      {
        "given": "Daniel O.",
        "family": "Vidal"
      },
      {
        "given": "Andrew",
        "family": "Burnette"
      },
      {
        "given": "Jennifer",
        "family": "Eschbacher"
      },
      {
        "given": "Beth",
        "family": "Hermes"
      },
      {
        "given": "Ardene",
        "family": "Noss"
      },
      {
        "given": "Rosy",
        "family": "Singh"
      },
      {
        "given": "Matthew L.",
        "family": "Anderson"
      },
      {
        "given": "Patricia D.",
        "family": "Castro"
      },
      {
        "given": "Michael",
        "family": "Ittmann"
      },
      {
        "given": "David",
        "family": "Huntsman"
      },
      {
        "given": "Bernard",
        "family": "Kohl"
      },
      {
        "given": "Xuan",
        "family": "Le"
      },
      {
        "given": "Richard",
        "family": "Thorp"
      },
      {
        "given": "Chris",
        "family": "Andry"
      },
      {
        "given": "Elizabeth R.",
        "family": "Duffy"
      },
      {
        "given": "Vladimir",
        "family": "Lyadov"
      },
      {
        "given": "Oxana",
        "family": "Paklina"
      },
      {
        "given": "Galiya",
        "family": "Setdikova"
      },
      {
        "given": "Alexey",
        "family": "Shabunin"
      },
      {
        "given": "Mikhail",
        "family": "Tavobilov"
      },
      {
        "given": "Christopher",
        "family": "McPherson"
      },
      {
        "given": "Ronald",
        "family": "Warnick"
      },
      {
        "given": "Ross",
        "family": "Berkowitz"
      },
      {
        "given": "Daniel",
        "family": "Cramer"
      },
      {
        "given": "Colleen",
        "family": "Feltmate"
      },
      {
        "given": "Neil",
        "family": "Horowitz"
      },
      {
        "given": "Adam",
        "family": "Kibel"
      },
      {
        "given": "Michael",
        "family": "Muto"
      },
      {
        "given": "Chandrajit P.",
        "family": "Raut"
      },
      {
        "given": "Andrei",
        "family": "Malykh"
      },
      {
        "given": "Jill S.",
        "family": "Barnholtz-Sloan"
      },
      {
        "given": "Wendi",
        "family": "Barrett"
      },
      {
        "given": "Karen",
        "family": "Devine"
      },
      {
        "given": "Jordonna",
        "family": "Fulop"
      },
      {
        "given": "Quinn T.",
        "family": "Ostrom"
      },
      {
        "given": "Kristen",
        "family": "Shimmel"
      },
      {
        "given": "Yingli",
        "family": "Wolinsky"
      },
      {
        "given": "Andrew E.",
        "family": "Sloan"
      },
      {
        "given": "Agostino",
        "family": "De Rose"
      },
      {
        "given": "Felice",
        "family": "Giuliante"
      },
      {
        "given": "Marc",
        "family": "Goodman"
      },
      {
        "given": "Beth Y.",
        "family": "Karlan"
      },
      {
        "given": "Curt H.",
        "family": "Hagedorn"
      },
      {
        "given": "John",
        "family": "Eckman"
      },
      {
        "given": "Jodi",
        "family": "Harr"
      },
      {
        "given": "Jerome",
        "family": "Myers"
      },
      {
        "given": "Kelinda",
        "family": "Tucker"
      },
      {
        "given": "Leigh Anne",
        "family": "Zach"
      },
      {
        "given": "Brenda",
        "family": "Deyarmin"
      },
      {
        "given": "Hai",
        "family": "Hu"
      },
      {
        "given": "Leonid",
        "family": "Kvecher"
      },
      {
        "given": "Caroline",
        "family": "Larson"
      },
      {
        "given": "Richard J.",
        "family": "Mural"
      },
      {
        "given": "Stella",
        "family": "Somiari"
      },
      {
        "given": "Ales",
        "family": "Vicha"
      },
      {
        "given": "Tomas",
        "family": "Zelinka"
      },
      {
        "given": "Joseph",
        "family": "Bennett"
      },
      {
        "given": "Mary",
        "family": "Iacocca"
      },
      {
        "given": "Brenda",
        "family": "Rabeno"
      },
      {
        "given": "Patricia",
        "family": "Swanson"
      },
      {
        "given": "Mathieu",
        "family": "Latour"
      },
      {
        "given": "Louis",
        "family": "Lacombe"
      },
      {
        "given": "Bernard",
        "family": "Têtu"
      },
      {
        "given": "Alain",
        "family": "Bergeron"
      },
      {
        "given": "Mary",
        "family": "McGraw"
      },
      {
        "given": "Susan M.",
        "family": "Staugaitis"
      },
      {
        "given": "John",
        "family": "Chabot"
      },
      {
        "given": "Hanina",
        "family": "Hibshoosh"
      },
      {
        "given": "Antonia",
        "family": "Sepulveda"
      },
      {
        "given": "Tao",
        "family": "Su"
      },
      {
        "given": "Timothy",
        "family": "Wang"
      },
      {
        "given": "Olga",
        "family": "Potapova"
      },
      {
        "given": "Olga",
        "family": "Voronina"
      },
      {
        "given": "Laurence",
        "family": "Desjardins"
      },
      {
        "given": "Odette",
        "family": "Mariani"
      },
      {
        "given": "Sergio",
        "family": "Roman-Roman"
      },
      {
        "given": "Xavier",
        "family": "Sastre"
      },
      {
        "given": "Marc-Henri",
        "family": "Stern"
      },
      {
        "given": "Feixiong",
        "family": "Cheng"
      },
      {
        "given": "Sabina",
        "family": "Signoretti"
      },
      {
        "given": "Andrew",
        "family": "Berchuck"
      },
      {
        "given": "Darell",
        "family": "Bigner"
      },
      {
        "given": "Eric",
        "family": "Lipp"
      },
      {
        "given": "Jeffrey",
        "family": "Marks"
      },
      {
        "given": "Shannon",
        "family": "McCall"
      },
      {
        "given": "Roger",
        "family": "McLendon"
      },
      {
        "given": "Angeles",
        "family": "Secord"
      },
      {
        "given": "Alexis",
        "family": "Sharp"
      },
      {
        "given": "Madhusmita",
        "family": "Behera"
      },
      {
        "given": "Daniel J.",
        "family": "Brat"
      },
      {
        "given": "Amy",
        "family": "Chen"
      },
      {
        "given": "Keith",
        "family": "Delman"
      },
      {
        "given": "Seth",
        "family": "Force"
      },
      {
        "given": "Fadlo",
        "family": "Khuri"
      },
      {
        "given": "Kelly",
        "family": "Magliocca"
      },
      {
        "given": "Shishir",
        "family": "Maithel"
      },
      {
        "given": "Jeffrey J.",
        "family": "Olson"
      },
      {
        "given": "Taofeek",
        "family": "Owonikoko"
      },
      {
        "given": "Alan",
        "family": "Pickens"
      },
      {
        "given": "Suresh",
        "family": "Ramalingam"
      },
      {
        "given": "Dong M.",
        "family": "Shin"
      },
      {
        "given": "Gabriel",
        "family": "Sica"
      },
      {
        "given": "Erwin G.",
        "family": "Van Meir"
      },
      {
        "given": "Hongzheng",
        "family": "Zhang"
      },
      {
        "given": "Wil",
        "family": "Eijckenboom"
      },
      {
        "given": "Ad",
        "family": "Gillis"
      },
      {
        "given": "Esther",
        "family": "Korpershoek"
      },
      {
        "given": "Leendert",
        "family": "Looijenga"
      },
      {
        "given": "Wolter",
        "family": "Oosterhuis"
      },
      {
        "given": "Hans",
        "family": "Stoop"
      },
      {
        "given": "Kim E.",
        "family": "van Kessel"
      },
      {
        "given": "Ellen C.",
        "family": "Zwarthoff"
      },
      {
        "given": "Chiara",
        "family": "Calatozzolo"
      },
      {
        "given": "Lucia",
        "family": "Cuppini"
      },
      {
        "given": "Stefania",
        "family": "Cuzzubbo"
      },
      {
        "given": "Francesco",
        "family": "DiMeco"
      },
      {
        "given": "Gaetano",
        "family": "Finocchiaro"
      },
      {
        "given": "Luca",
        "family": "Mattei"
      },
      {
        "given": "Alessandro",
        "family": "Perin"
      },
      {
        "given": "Bianca",
        "family": "Pollo"
      },
      {
        "given": "Chu",
        "family": "Chen"
      },
      {
        "given": "John",
        "family": "Houck"
      },
      {
        "given": "Pawadee",
        "family": "Lohavanichbutr"
      },
      {
        "given": "Arndt",
        "family": "Hartmann"
      },
      {
        "given": "Christine",
        "family": "Stoehr"
      },
      {
        "given": "Robert",
        "family": "Stoehr"
      },
      {
        "given": "Helge",
        "family": "Taubert"
      },
      {
        "given": "Sven",
        "family": "Wach"
      },
      {
        "given": "Bernd",
        "family": "Wullich"
      },
      {
        "given": "Witold",
        "family": "Kycler"
      },
      {
        "given": "Dawid",
        "family": "Murawa"
      },
      {
        "given": "Maciej",
        "family": "Wiznerowicz"
      },
      {
        "given": "Ki",
        "family": "Chung"
      },
      {
        "given": "W. Jeffrey",
        "family": "Edenfield"
      },
      {
        "given": "Julie",
        "family": "Martin"
      },
      {
        "given": "Eric",
        "family": "Baudin"
      },
      {
        "given": "Glenn",
        "family": "Bubley"
      },
      {
        "given": "Raphael",
        "family": "Bueno"
      },
      {
        "given": "Assunta",
        "family": "De Rienzo"
      },
      {
        "given": "William G.",
        "family": "Richards"
      },
      {
        "given": "Steven",
        "family": "Kalkanis"
      },
      {
        "given": "Tom",
        "family": "Mikkelsen"
      },
      {
        "given": "Houtan",
        "family": "Noushmehr"
      },
      {
        "given": "Lisa",
        "family": "Scarpace"
      },
      {
        "given": "Nicolas",
        "family": "Girard"
      },
      {
        "given": "Marta",
        "family": "Aymerich"
      },
      {
        "given": "Elias",
        "family": "Campo"
      },
      {
        "given": "Eva",
        "family": "Giné"
      },
      {
        "given": "Armando López",
        "family": "Guillermo"
      },
      {
        "given": "Nguyen",
        "family": "Van Bang"
      },
      {
        "given": "Phan Thi",
        "family": "Hanh"
      },
      {
        "given": "Bui Duc",
        "family": "Phu"
      },
      {
        "given": "Yufang",
        "family": "Tang"
      },
      {
        "given": "Howard",
        "family": "Colman"
      },
      {
        "given": "Kimberley",
        "family": "Evason"
      },
      {
        "given": "Peter R.",
        "family": "Dottino"
      },
      {
        "given": "John A.",
        "family": "Martignetti"
      },
      {
        "given": "Hani",
        "family": "Gabra"
      },
      {
        "given": "Hartmut",
        "family": "Juhl"
      },
      {
        "given": "Teniola",
        "family": "Akeredolu"
      },
      {
        "given": "Serghei",
        "family": "Stepa"
      },
      {
        "given": "Dave",
        "family": "Hoon"
      },
      {
        "given": "Keunsoo",
        "family": "Ahn"
      },
      {
        "given": "Koo Jeong",
        "family": "Kang"
      },
      {
        "given": "Felix",
        "family": "Beuschlein"
      },
      {
        "given": "Anne",
        "family": "Breggia"
      },
      {
        "given": "Michael",
        "family": "Birrer"
      },
      {
        "given": "Debra",
        "family": "Bell"
      },
      {
        "given": "Mitesh",
        "family": "Borad"
      },
      {
        "given": "Alan H.",
        "family": "Bryce"
      },
      {
        "given": "Erik",
        "family": "Castle"
      },
      {
        "given": "Vishal",
        "family": "Chandan"
      },
      {
        "given": "John",
        "family": "Cheville"
      },
      {
        "given": "John A.",
        "family": "Copland"
      },
      {
        "given": "Michael",
        "family": "Farnell"
      },
      {
        "given": "Thomas",
        "family": "Flotte"
      },
      {
        "given": "Nasra",
        "family": "Giama"
      },
      {
        "given": "Thai",
        "family": "Ho"
      },
      {
        "given": "Michael",
        "family": "Kendrick"
      },
      {
        "given": "Jean-Pierre",
        "family": "Kocher"
      },
      {
        "given": "Karla",
        "family": "Kopp"
      },
      {
        "given": "Catherine",
        "family": "Moser"
      },
      {
        "given": "David",
        "family": "Nagorney"
      },
      {
        "given": "Daniel",
        "family": "O’Brien"
      },
      {
        "given": "Brian Patrick",
        "family": "O’Neill"
      },
      {
        "given": "Tushar",
        "family": "Patel"
      },
      {
        "given": "Gloria",
        "family": "Petersen"
      },
      {
        "given": "Florencia",
        "family": "Que"
      },
      {
        "given": "Michael",
        "family": "Rivera"
      },
      {
        "given": "Lewis",
        "family": "Roberts"
      },
      {
        "given": "Robert",
        "family": "Smallridge"
      },
      {
        "given": "Thomas",
        "family": "Smyrk"
      },
      {
        "given": "Melissa",
        "family": "Stanton"
      },
      {
        "given": "R. Houston",
        "family": "Thompson"
      },
      {
        "given": "Michael",
        "family": "Torbenson"
      },
      {
        "given": "Ju Dong",
        "family": "Yang"
      },
      {
        "given": "Lizhi",
        "family": "Zhang"
      },
      {
        "given": "Fadi",
        "family": "Brimo"
      },
      {
        "given": "Jaffer A.",
        "family": "Ajani"
      },
      {
        "given": "Ana Maria",
        "family": "Angulo Gonzalez"
      },
      {
        "given": "Carmen",
        "family": "Behrens"
      },
      {
        "given": "Jolanta",
        "family": "Bondaruk"
      },
      {
        "given": "Russell",
        "family": "Broaddus"
      },
      {
        "given": "Bogdan",
        "family": "Czerniak"
      },
      {
        "given": "Bita",
        "family": "Esmaeli"
      },
      {
        "given": "Junya",
        "family": "Fujimoto"
      },
      {
        "given": "Jeffrey",
        "family": "Gershenwald"
      },
      {
        "given": "Charles",
        "family": "Guo"
      },
      {
        "given": "Alexander J.",
        "family": "Lazar"
      },
      {
        "given": "Christopher",
        "family": "Logothetis"
      },
      {
        "given": "Funda",
        "family": "Meric-Bernstam"
      },
      {
        "given": "Cesar",
        "family": "Moran"
      },
      {
        "given": "Lois",
        "family": "Ramondetta"
      },
      {
        "given": "David",
        "family": "Rice"
      },
      {
        "given": "Anil",
        "family": "Sood"
      },
      {
        "given": "Pheroze",
        "family": "Tamboli"
      },
      {
        "given": "Timothy",
        "family": "Thompson"
      },
      {
        "given": "Patricia",
        "family": "Troncoso"
      },
      {
        "given": "Anne",
        "family": "Tsao"
      },
      {
        "given": "Ignacio",
        "family": "Wistuba"
      },
      {
        "given": "Candace",
        "family": "Carter"
      },
      {
        "given": "Lauren",
        "family": "Haydu"
      },
      {
        "given": "Peter",
        "family": "Hersey"
      },
      {
        "given": "Valerie",
        "family": "Jakrot"
      },
      {
        "given": "Hojabr",
        "family": "Kakavand"
      },
      {
        "given": "Richard",
        "family": "Kefford"
      },
      {
        "given": "Kenneth",
        "family": "Lee"
      },
      {
        "given": "Georgina",
        "family": "Long"
      },
      {
        "given": "Graham",
        "family": "Mann"
      },
      {
        "given": "Michael",
        "family": "Quinn"
      },
      {
        "given": "Robyn",
        "family": "Saw"
      },
      {
        "given": "Richard",
        "family": "Scolyer"
      },
      {
        "given": "Kerwin",
        "family": "Shannon"
      },
      {
        "given": "Andrew",
        "family": "Spillane"
      },
      {
        "given": "Jonathan",
        "family": "Stretch"
      },
      {
        "given": "Maria",
        "family": "Synott"
      },
      {
        "given": "John",
        "family": "Thompson"
      },
      {
        "given": "James",
        "family": "Wilmott"
      },
      {
        "given": "Hikmat",
        "family": "Al-Ahmadie"
      },
      {
        "given": "Timothy A.",
        "family": "Chan"
      },
      {
        "given": "Ronald",
        "family": "Ghossein"
      },
      {
        "given": "Anuradha",
        "family": "Gopalan"
      },
      {
        "given": "Douglas A.",
        "family": "Levine"
      },
      {
        "given": "Victor",
        "family": "Reuter"
      },
      {
        "given": "Samuel",
        "family": "Singer"
      },
      {
        "given": "Bhuvanesh",
        "family": "Singh"
      },
      {
        "given": "Nguyen Viet",
        "family": "Tien"
      },
      {
        "given": "Thomas",
        "family": "Broudy"
      },
      {
        "given": "Cyrus",
        "family": "Mirsaidi"
      },
      {
        "given": "Praveen",
        "family": "Nair"
      },
      {
        "given": "Paul",
        "family": "Drwiega"
      },
      {
        "given": "Judy",
        "family": "Miller"
      },
      {
        "given": "Jennifer",
        "family": "Smith"
      },
      {
        "given": "Howard",
        "family": "Zaren"
      },
      {
        "given": "Joong-Won",
        "family": "Park"
      },
      {
        "given": "Nguyen Phi",
        "family": "Hung"
      },
      {
        "given": "Electron",
        "family": "Kebebew"
      },
      {
        "given": "W. Marston",
        "family": "Linehan"
      },
      {
        "given": "Adam R.",
        "family": "Metwalli"
      },
      {
        "given": "Karel",
        "family": "Pacak"
      },
      {
        "given": "Peter A.",
        "family": "Pinto"
      },
      {
        "given": "Mark",
        "family": "Schiffman"
      },
      {
        "given": "Laura S.",
        "family": "Schmidt"
      },
      {
        "given": "Cathy D.",
        "family": "Vocke"
      },
      {
        "given": "Nicolas",
        "family": "Wentzensen"
      },
      {
        "given": "Robert",
        "family": "Worrell"
      },
      {
        "given": "Hannah",
        "family": "Yang"
      },
      {
        "given": "Marc",
        "family": "Moncrieff"
      },
      {
        "given": "Chandra",
        "family": "Goparaju"
      },
      {
        "given": "Jonathan",
        "family": "Melamed"
      },
      {
        "given": "Harvey",
        "family": "Pass"
      },
      {
        "given": "Natalia",
        "family": "Botnariuc"
      },
      {
        "given": "Irina",
        "family": "Caraman"
      },
      {
        "given": "Mircea",
        "family": "Cernat"
      },
      {
        "given": "Inga",
        "family": "Chemencedji"
      },
      {
        "given": "Adrian",
        "family": "Clipca"
      },
      {
        "given": "Serghei",
        "family": "Doruc"
      },
      {
        "given": "Ghenadie",
        "family": "Gorincioi"
      },
      {
        "given": "Sergiu",
        "family": "Mura"
      },
      {
        "given": "Maria",
        "family": "Pirtac"
      },
      {
        "given": "Irina",
        "family": "Stancul"
      },
      {
        "given": "Diana",
        "family": "Tcaciuc"
      },
      {
        "given": "Monique",
        "family": "Albert"
      },
      {
        "given": "Iakovina",
        "family": "Alexopoulou"
      },
      {
        "given": "Angel",
        "family": "Arnaout"
      },
      {
        "given": "John",
        "family": "Bartlett"
      },
      {
        "given": "Jay",
        "family": "Engel"
      },
      {
        "given": "Sebastien",
        "family": "Gilbert"
      },
      {
        "given": "Jeremy",
        "family": "Parfitt"
      },
      {
        "given": "Harman",
        "family": "Sekhon"
      },
      {
        "given": "George",
        "family": "Thomas"
      },
      {
        "given": "Doris M.",
        "family": "Rassl"
      },
      {
        "given": "Robert C.",
        "family": "Rintoul"
      },
      {
        "given": "Carlo",
        "family": "Bifulco"
      },
      {
        "given": "Raina",
        "family": "Tamakawa"
      },
      {
        "given": "Walter",
        "family": "Urba"
      },
      {
        "given": "Nicholas",
        "family": "Hayward"
      },
      {
        "given": "Henri",
        "family": "Timmers"
      },
      {
        "given": "Anna",
        "family": "Antenucci"
      },
      {
        "given": "Francesco",
        "family": "Facciolo"
      },
      {
        "given": "Gianluca",
        "family": "Grazi"
      },
      {
        "given": "Mirella",
        "family": "Marino"
      },
      {
        "given": "Roberta",
        "family": "Merola"
      },
      {
        "given": "Ronald",
        "family": "de Krijger"
      },
      {
        "given": "Anne-Paule",
        "family": "Gimenez-Roqueplo"
      },
      {
        "given": "Alain",
        "family": "Piché"
      },
      {
        "given": "Simone",
        "family": "Chevalier"
      },
      {
        "given": "Ginette",
        "family": "McKercher"
      },
      {
        "given": "Kivanc",
        "family": "Birsoy"
      },
      {
        "given": "Gene",
        "family": "Barnett"
      },
      {
        "given": "Cathy",
        "family": "Brewer"
      },
      {
        "given": "Carol",
        "family": "Farver"
      },
      {
        "given": "Theresa",
        "family": "Naska"
      },
      {
        "given": "Nathan A.",
        "family": "Pennell"
      },
      {
        "given": "Daniel",
        "family": "Raymond"
      },
      {
        "given": "Cathy",
        "family": "Schilero"
      },
      {
        "given": "Kathy",
        "family": "Smolenski"
      },
      {
        "given": "Felicia",
        "family": "Williams"
      },
      {
        "given": "Carl",
        "family": "Morrison"
      },
      {
        "given": "Jeffrey A.",
        "family": "Borgia"
      },
      {
        "given": "Michael J.",
        "family": "Liptay"
      },
      {
        "given": "Mark",
        "family": "Pool"
      },
      {
        "given": "Christopher W.",
        "family": "Seder"
      },
      {
        "given": "Kerstin",
        "family": "Junker"
      },
      {
        "given": "Larsson",
        "family": "Omberg"
      },
      {
        "given": "Mikhail",
        "family": "Dinkin"
      },
      {
        "given": "George",
        "family": "Manikhas"
      },
      {
        "given": "Domenico",
        "family": "Alvaro"
      },
      {
        "given": "Maria Consiglia",
        "family": "Bragazzi"
      },
      {
        "given": "Vincenzo",
        "family": "Cardinale"
      },
      {
        "given": "Guido",
        "family": "Carpino"
      },
      {
        "given": "Eugenio",
        "family": "Gaudio"
      },
      {
        "given": "David",
        "family": "Chesla"
      },
      {
        "given": "Sandra",
        "family": "Cottingham"
      },
      {
        "given": "Michael",
        "family": "Dubina"
      },
      {
        "given": "Fedor",
        "family": "Moiseenko"
      },
      {
        "given": "Renumathy",
        "family": "Dhanasekaran"
      },
      {
        "given": "Karl-Friedrich",
        "family": "Becker"
      },
      {
        "given": "Klaus-Peter",
        "family": "Janssen"
      },
      {
        "given": "Julia",
        "family": "Slotta-Huspenina"
      },
      {
        "given": "Mohamed H.",
        "family": "Abdel-Rahman"
      },
      {
        "given": "Dina",
        "family": "Aziz"
      },
      {
        "given": "Sue",
        "family": "Bell"
      },
      {
        "given": "Colleen M.",
        "family": "Cebulla"
      },
      {
        "given": "Amy",
        "family": "Davis"
      },
      {
        "given": "Rebecca",
        "family": "Duell"
      },
      {
        "given": "J. Bradley",
        "family": "Elder"
      },
      {
        "given": "Joe",
        "family": "Hilty"
      },
      {
        "given": "Bahavna",
        "family": "Kumar"
      },
      {
        "given": "James",
        "family": "Lang"
      },
      {
        "given": "Norman L.",
        "family": "Lehman"
      },
      {
        "given": "Randy",
        "family": "Mandt"
      },
      {
        "given": "Phuong",
        "family": "Nguyen"
      },
      {
        "given": "Robert",
        "family": "Pilarski"
      },
      {
        "given": "Karan",
        "family": "Rai"
      },
      {
        "given": "Lynn",
        "family": "Schoenfield"
      },
      {
        "given": "Kelly",
        "family": "Senecal"
      },
      {
        "given": "Paul",
        "family": "Wakely"
      },
      {
        "given": "Paul",
        "family": "Hansen"
      },
      {
        "given": "Ronald",
        "family": "Lechan"
      },
      {
        "given": "James",
        "family": "Powers"
      },
      {
        "given": "Arthur",
        "family": "Tischler"
      },
      {
        "given": "William E.",
        "family": "Grizzle"
      },
      {
        "given": "Katherine C.",
        "family": "Sexton"
      },
      {
        "given": "Alison",
        "family": "Kastl"
      },
      {
        "given": "Joel",
        "family": "Henderson"
      },
      {
        "given": "Sima",
        "family": "Porten"
      },
      {
        "given": "Jens",
        "family": "Waldmann"
      },
      {
        "given": "Martin",
        "family": "Fassnacht"
      },
      {
        "given": "Sylvia L.",
        "family": "Asa"
      },
      {
        "given": "Dirk",
        "family": "Schadendorf"
      },
      {
        "given": "Marta",
        "family": "Couce"
      },
      {
        "given": "Markus",
        "family": "Graefen"
      },
      {
        "given": "Hartwig",
        "family": "Huland"
      },
      {
        "given": "Guido",
        "family": "Sauter"
      },
      {
        "given": "Thorsten",
        "family": "Schlomm"
      },
      {
        "given": "Ronald",
        "family": "Simon"
      },
      {
        "given": "Pierre",
        "family": "Tennstedt"
      },
      {
        "given": "Oluwole",
        "family": "Olabode"
      },
      {
        "given": "Mark",
        "family": "Nelson"
      },
      {
        "given": "Oliver",
        "family": "Bathe"
      },
      {
        "given": "Peter R.",
        "family": "Carroll"
      },
      {
        "given": "June M.",
        "family": "Chan"
      },
      {
        "given": "Philip",
        "family": "Disaia"
      },
      {
        "given": "Pat",
        "family": "Glenn"
      },
      {
        "given": "Robin K.",
        "family": "Kelley"
      },
      {
        "given": "Charles N.",
        "family": "Landen"
      },
      {
        "given": "Joanna",
        "family": "Phillips"
      },
      {
        "given": "Michael",
        "family": "Prados"
      },
      {
        "given": "Jeffry",
        "family": "Simko"
      },
      {
        "given": "Karen",
        "family": "Smith-McCune"
      },
      {
        "given": "Scott",
        "family": "VandenBerg"
      },
      {
        "given": "Kevin",
        "family": "Roggin"
      },
      {
        "given": "Ashley",
        "family": "Fehrenbach"
      },
      {
        "given": "Ady",
        "family": "Kendler"
      },
      {
        "given": "Suzanne",
        "family": "Sifri"
      },
      {
        "given": "Ruth",
        "family": "Steele"
      },
      {
        "given": "Antonio",
        "family": "Jimeno"
      },
      {
        "given": "Francis",
        "family": "Carey"
      },
      {
        "given": "Ian",
        "family": "Forgie"
      },
      {
        "given": "Massimo",
        "family": "Mannelli"
      },
      {
        "given": "Michael",
        "family": "Carney"
      },
      {
        "given": "Brenda",
        "family": "Hernandez"
      },
      {
        "given": "Benito",
        "family": "Campos"
      },
      {
        "given": "Christel",
        "family": "Herold-Mende"
      },
      {
        "given": "Christin",
        "family": "Jungk"
      },
      {
        "given": "Andreas",
        "family": "Unterberg"
      },
      {
        "given": "Andreas",
        "family": "von Deimling"
      },
      {
        "given": "Aaron",
        "family": "Bossler"
      },
      {
        "given": "Joseph",
        "family": "Galbraith"
      },
      {
        "given": "Laura",
        "family": "Jacobus"
      },
      {
        "given": "Michael",
        "family": "Knudson"
      },
      {
        "given": "Tina",
        "family": "Knutson"
      },
      {
        "given": "Deqin",
        "family": "Ma"
      },
      {
        "given": "Mohammed",
        "family": "Milhem"
      },
      {
        "given": "Rita",
        "family": "Sigmund"
      },
      {
        "given": "Andrew K.",
        "family": "Godwin"
      },
      {
        "given": "Rashna",
        "family": "Madan"
      },
      {
        "given": "Howard G.",
        "family": "Rosenthal"
      },
      {
        "given": "Clement",
        "family": "Adebamowo"
      },
      {
        "given": "Sally N.",
        "family": "Adebamowo"
      },
      {
        "given": "Alex",
        "family": "Boussioutas"
      },
      {
        "given": "David",
        "family": "Beer"
      },
      {
        "given": "Thomas",
        "family": "Giordano"
      },
      {
        "given": "Anne-Marie",
        "family": "Mes-Masson"
      },
      {
        "given": "Fred",
        "family": "Saad"
      },
      {
        "given": "Therese",
        "family": "Bocklage"
      },
      {
        "given": "Lisa",
        "family": "Landrum"
      },
      {
        "given": "Robert",
        "family": "Mannel"
      },
      {
        "given": "Kathleen",
        "family": "Moore"
      },
      {
        "given": "Katherine",
        "family": "Moxley"
      },
      {
        "given": "Russel",
        "family": "Postier"
      },
      {
        "given": "Joan",
        "family": "Walker"
      },
      {
        "given": "Rosemary",
        "family": "Zuna"
      },
      {
        "given": "Michael",
        "family": "Feldman"
      },
      {
        "given": "Federico",
        "family": "Valdivieso"
      },
      {
        "given": "Rajiv",
        "family": "Dhir"
      },
      {
        "given": "James",
        "family": "Luketich"
      },
      {
        "given": "Edna M.",
        "family": "Mora Pinero"
      },
      {
        "given": "Mario",
        "family": "Quintero-Aguilo"
      },
      {
        "suffix": "Jr.",
        "given": "Carlos Gilberto",
        "family": "Carlotti"
      },
      {
        "given": "Jose Sebastião",
        "family": "Dos Santos"
      },
      {
        "given": "Rafael",
        "family": "Kemp"
      },
      {
        "given": "Ajith",
        "family": "Sankarankuty"
      },
      {
        "given": "Daniela",
        "family": "Tirapelli"
      },
      {
        "given": "James",
        "family": "Catto"
      },
      {
        "given": "Kathy",
        "family": "Agnew"
      },
      {
        "given": "Elizabeth",
        "family": "Swisher"
      },
      {
        "given": "Jenette",
        "family": "Creaney"
      },
      {
        "given": "Bruce",
        "family": "Robinson"
      },
      {
        "given": "Carl Simon",
        "family": "Shelley"
      },
      {
        "given": "Eryn M.",
        "family": "Godwin"
      },
      {
        "given": "Sara",
        "family": "Kendall"
      },
      {
        "given": "Cassaundra",
        "family": "Shipman"
      },
      {
        "given": "Carol",
        "family": "Bradford"
      },
      {
        "given": "Thomas",
        "family": "Carey"
      },
      {
        "given": "Andrea",
        "family": "Haddad"
      },
      {
        "given": "Jeffey",
        "family": "Moyer"
      },
      {
        "given": "Lisa",
        "family": "Peterson"
      },
      {
        "given": "Mark",
        "family": "Prince"
      },
      {
        "given": "Laura",
        "family": "Rozek"
      },
      {
        "given": "Gregory",
        "family": "Wolf"
      },
      {
        "given": "Rayleen",
        "family": "Bowman"
      },
      {
        "given": "Kwun M.",
        "family": "Fong"
      },
      {
        "given": "Ian",
        "family": "Yang"
      },
      {
        "given": "Robert",
        "family": "Korst"
      },
      {
        "given": "W. Kimryn",
        "family": "Rathmell"
      },
      {
        "given": "J. Leigh",
        "family": "Fantacone-Campbell"
      },
      {
        "given": "Jeffrey A.",
        "family": "Hooke"
      },
      {
        "given": "Albert J.",
        "family": "Kovatich"
      },
      {
        "given": "Craig D.",
        "family": "Shriver"
      },
      {
        "given": "John",
        "family": "DiPersio"
      },
      {
        "given": "Bettina",
        "family": "Drake"
      },
      {
        "given": "Ramaswamy",
        "family": "Govindan"
      },
      {
        "given": "Sharon",
        "family": "Heath"
      },
      {
        "given": "Timothy",
        "family": "Ley"
      },
      {
        "given": "Brian",
        "family": "Van Tine"
      },
      {
        "given": "Peter",
        "family": "Westervelt"
      },
      {
        "given": "Mark A.",
        "family": "Rubin"
      },
      {
        "given": "Jung Il",
        "family": "Lee"
      },
      {
        "given": "Natália D.",
        "family": "Aredes"
      },
      {
        "given": "Armaz",
        "family": "Mariamidze"
      }
    ],
    "container-title": "Cell Systems",
    "language": "en",
    "issued": {
      "date-parts": [
        [
          2018,
          3
        ]
      ]
    },
    "URL": "https://doi.org/gf9twn",
    "container-title-short": "Cell Systems",
    "PMCID": "PMC6075717",
    "PMID": "29596782",
    "id": "cDnF3a5Q",
    "note": "This CSL Item was generated by Manubot v0.5.5 from its persistent identifier (standard_id).\nstandard_id: doi:10.1016/j.cels.2018.03.002"
  },
  {
    "publisher": "Proceedings of the National Academy of Sciences",
    "issue": "50",
    "abstract": "<jats:title>Significance</jats:title>\n          <jats:p>Modern large-scale sequencing of human cancers seeks to comprehensively discover mutated genes that confer a selective advantage to cancer cells. Key to this effort has been development of computational algorithms to find genes that drive cancer based on their patterns of mutation in large patient cohorts. Because there is no generally accepted gold standard of driver genes, it has been difficult to quantitatively compare these methods. We present a machine-learning–based method for driver gene prediction and a protocol to evaluate and compare prediction methods. Our results suggest that most current methods do not adequately account for heterogeneity in the number of mutations expected by chance and consequently yield many false-positive calls, particularly in cancers with high mutation rate.</jats:p>",
    "DOI": "10.1073/pnas.1616440113",
    "type": "article-journal",
    "page": "14330-14335",
    "source": "Crossref",
    "title": "Evaluating the evaluation of cancer driver genes",
    "volume": "113",
    "author": [
      {
        "given": "Collin J.",
        "family": "Tokheim"
      },
      {
        "given": "Nickolas",
        "family": "Papadopoulos"
      },
      {
        "given": "Kenneth W.",
        "family": "Kinzler"
      },
      {
        "given": "Bert",
        "family": "Vogelstein"
      },
      {
        "given": "Rachel",
        "family": "Karchin"
      }
    ],
    "container-title": "Proceedings of the National Academy of Sciences",
    "language": "en",
    "issued": {
      "date-parts": [
        [
          2016,
          11,
          22
        ]
      ]
    },
    "URL": "https://doi.org/f9d77w",
    "container-title-short": "Proc. Natl. Acad. Sci. U.S.A.",
    "PMCID": "PMC5167163",
    "PMID": "27911828",
    "id": "MnWpJEWE",
    "note": "This CSL Item was generated by Manubot v0.5.5 from its persistent identifier (standard_id).\nstandard_id: doi:10.1073/pnas.1616440113"
  },
  {
    "publisher": "Oxford University Press (OUP)",
    "issue": "1",
    "abstract": "<jats:title>Abstract</jats:title>\n               <jats:sec>\n                  <jats:title>Background</jats:title>\n                  <jats:p>IDH-mutant lower-grade gliomas (LGGs) evolve under the selective pressure of therapy, but well-characterized patient-derived cells (PDCs) modeling evolutionary stages are lacking. IDH-mutant LGGs may develop therapeutic resistance associated with chemotherapy-driven hypermutation and malignant progression. The aim of this study was to establish and characterize PDCs, single-cell-derived PDCs (scPDCs), and xenografts (PDX) of IDH1-mutant recurrences representing distinct stages of tumor evolution.</jats:p>\n               </jats:sec>\n               <jats:sec>\n                  <jats:title>Methods</jats:title>\n                  <jats:p>We derived and validated cell cultures from IDH1-mutant recurrences of astrocytoma and oligodendroglioma. We used exome sequencing and phylogenetic reconstruction to examine the evolutionary stage represented by PDCs, scPDCs, and PDX relative to corresponding spatiotemporal tumor tissue and germline DNA. PDCs were also characterized for growth and tumor immortality phenotypes, and PDX were examined histologically.</jats:p>\n               </jats:sec>\n               <jats:sec>\n                  <jats:title>Results</jats:title>\n                  <jats:p>The integrated astrocytoma phylogeny revealed 2 independent founder clonal expansions of hypermutated (HM) cells in tumor tissue that are faithfully represented by independent PDCs. The oligodendroglioma phylogeny showed more than 4000 temozolomide-associated mutations shared among tumor samples, PDCs, scPDCs, and PDX, suggesting a shared monoclonal origin. The PDCs from both subtypes exhibited hallmarks of tumorigenesis, retention of subtype-defining genomic features, production of 2-hydroxyglutarate, and subtype-specific telomere maintenance mechanisms that confer tumor cell immortality. The oligodendroglioma PDCs formed infiltrative intracranial tumors with characteristic histology.</jats:p>\n               </jats:sec>\n               <jats:sec>\n                  <jats:title>Conclusions</jats:title>\n                  <jats:p>These PDCs, scPDCs, and PDX are unique and versatile community resources that model the heterogeneous clonal origins and functions of recurrent IDH1-mutant LGGs. The integrated phylogenies advance our knowledge of the complex evolution and immense mutational load of IDH1-mutant HM glioma.</jats:p>\n               </jats:sec>",
    "DOI": "10.1093/noajnl/vdaa088",
    "type": "article-journal",
    "source": "Crossref",
    "title": "Patient-derived cells from recurrent tumors that model the evolution of IDH-mutant glioma",
    "volume": "2",
    "author": [
      {
        "given": "Lindsey E",
        "family": "Jones"
      },
      {
        "given": "Stephanie",
        "family": "Hilz"
      },
      {
        "given": "Matthew R",
        "family": "Grimmer"
      },
      {
        "given": "Tali",
        "family": "Mazor"
      },
      {
        "given": "Chloé",
        "family": "Najac"
      },
      {
        "given": "Joydeep",
        "family": "Mukherjee"
      },
      {
        "given": "Andrew",
        "family": "McKinney"
      },
      {
        "given": "Tracy",
        "family": "Chow"
      },
      {
        "given": "Russell O",
        "family": "Pieper"
      },
      {
        "given": "Sabrina M",
        "family": "Ronen"
      },
      {
        "given": "Susan M",
        "family": "Chang"
      },
      {
        "given": "Joanna J",
        "family": "Phillips"
      },
      {
        "given": "Joseph F",
        "family": "Costello"
      }
    ],
    "container-title": "Neuro-Oncology Advances",
    "language": "en",
    "issued": {
      "date-parts": [
        [
          2020,
          1,
          1
        ]
      ]
    },
    "URL": "https://doi.org/gsfw2p",
    "PMCID": "PMC7462278",
    "PMID": "32904945",
    "id": "HQx0QuE4",
    "note": "This CSL Item was generated by Manubot v0.5.5 from its persistent identifier (standard_id).\nstandard_id: doi:10.1093/noajnl/vdaa088"
  },
  {
    "publisher": "American Association for the Advancement of Science (AAAS)",
    "issue": "6127",
    "DOI": "10.1126/science.1235122",
    "type": "article-journal",
    "page": "1546-1558",
    "source": "Crossref",
    "title": "Cancer Genome Landscapes",
    "volume": "339",
    "author": [
      {
        "given": "B.",
        "family": "Vogelstein"
      },
      {
        "given": "N.",
        "family": "Papadopoulos"
      },
      {
        "given": "V. E.",
        "family": "Velculescu"
      },
      {
        "given": "S.",
        "family": "Zhou"
      },
      {
        "given": "L. A.",
        "family": "Diaz"
      },
      {
        "given": "K. W.",
        "family": "Kinzler"
      }
    ],
    "container-title": "Science",
    "language": "en",
    "issued": {
      "date-parts": [
        [
          2013,
          3,
          28
        ]
      ]
    },
    "URL": "https://doi.org/6rg",
    "container-title-short": "Science",
    "PMCID": "PMC3749880",
    "PMID": "23539594",
    "id": "809OyWlC",
    "note": "This CSL Item was generated by Manubot v0.5.5 from its persistent identifier (standard_id).\nstandard_id: doi:10.1126/science.1235122"
  },
  {
    "publisher": "Annual Reviews",
    "issue": "1",
    "abstract": "<jats:p> Epidermal growth factor receptor (EGFR) is a transmembrane protein with cytoplasmic kinase activity that transduces important growth factor signaling from the extracellular milieu to the cell. Given that more than 60% of non–small cell lung carcinomas (NSCLCs) express EGFR, EGFR has become an important therapeutic target for the treatment of these tumors. Inhibitors that target the kinase domain of EGFR have been developed and are clinically active. More importantly, such tyrosine kinase inhibitors (TKIs) are especially effective in patients whose tumors harbor activating mutations in the tyrosine kinase domain of the EGFR gene. More recent trials have suggested that for advanced NSCLC patients with EGFR mutant tumors, initial therapy with a TKI instead of chemotherapy may be the best choice of treatment. Therefore, mutation testing is mandatory to identify these patients, given that selection based only on clinico-pathologic characteristics is inadequate. We review the role of EGFR mutations in the diagnosis and management of NSCLC. </jats:p>",
    "DOI": "10.1146/annurev-pathol-011110-130206",
    "type": "article-journal",
    "page": "49-69",
    "source": "Crossref",
    "title": "EGFR Mutations and Lung Cancer",
    "volume": "6",
    "author": [
      {
        "given": "Gilda",
        "family": "da Cunha Santos"
      },
      {
        "given": "Frances A.",
        "family": "Shepherd"
      },
      {
        "given": "Ming Sound",
        "family": "Tsao"
      }
    ],
    "container-title": "Annual Review of Pathology: Mechanisms of Disease",
    "language": "en",
    "issued": {
      "date-parts": [
        [
          2011,
          2,
          28
        ]
      ]
    },
    "URL": "https://doi.org/dd359s",
    "container-title-short": "Annu. Rev. Pathol. Mech. Dis.",
    "PMID": "20887192",
    "id": "qtYNZ2Q2",
    "note": "This CSL Item was generated by Manubot v0.5.5 from its persistent identifier (standard_id).\nstandard_id: doi:10.1146/annurev-pathol-011110-130206"
  },
  {
    "publisher": "Springer Science and Business Media LLC",
    "issue": "4",
    "DOI": "10.1186/gb-2011-12-4-r41",
    "type": "article-journal",
    "source": "Crossref",
    "title": "GISTIC2.0 facilitates sensitive and confident localization of the targets of focal somatic copy-number alteration in human cancers",
    "volume": "12",
    "author": [
      {
        "given": "Craig H",
        "family": "Mermel"
      },
      {
        "given": "Steven E",
        "family": "Schumacher"
      },
      {
        "given": "Barbara",
        "family": "Hill"
      },
      {
        "given": "Matthew L",
        "family": "Meyerson"
      },
      {
        "given": "Rameen",
        "family": "Beroukhim"
      },
      {
        "given": "Gad",
        "family": "Getz"
      }
    ],
    "container-title": "Genome Biology",
    "language": "en",
    "issued": {
      "date-parts": [
        [
          2011,
          4
        ]
      ]
    },
    "URL": "https://doi.org/dzhjqh",
    "container-title-short": "Genome Biol",
    "PMCID": "PMC3218867",
    "PMID": "21527027",
    "id": "rDV1hhfF",
    "note": "This CSL Item was generated by Manubot v0.5.5 from its persistent identifier (standard_id).\nstandard_id: doi:10.1186/gb-2011-12-4-r41"
  }
]
